local_cname/__init__.py
local_cname/__main__.py
local_cname/cli.py
local_cnames-0.4.dist-info/METADATA
local_cnames-0.4.dist-info/RECORD
local_cnames-0.4.dist-info/WHEEL
local_cnames-0.4.dist-info/entry_points.txt
local_cnames-0.4.dist-info/top_level.txt
