Metadata-Version: 2.1
Name: local-cnames
Version: 0.4
Summary: Helper script to emulate a local CNAME DNS by writing to /etc/hosts
Home-page: https://github.com/evlon/local-cname
Author: evlion@qq.com
Author-email: UNKNOWN
License: GNU General Public License v3 (GPLv3)
Keywords: dns hosts local
Platform: UNKNOWN
Classifier: Programming Language :: Python
Classifier: Programming Language :: Python :: 3.4
Classifier: Programming Language :: Python :: 3.5
Classifier: Programming Language :: Python :: 3.6
Classifier: Intended Audience :: Developers
Classifier: Development Status :: 3 - Alpha
Classifier: Operating System :: POSIX
Requires-Dist: clickclick
